<?xml version="1.0" encoding="UTF-8"?>
<STORE URL="http://www.migvanhome.co.il/" DATE="17/09/2017" NAME="BestStore" STATUS="ONLINE">
  <PRODUCTS>
    <PRODUCT>
      <PRODUCT_URL>http://www.migvanhome.co.il/product.php?pid=616</PRODUCT_URL>
      <PRODUCT_NAME>נורה ראשית לרכב H1 תוצרת Philips דגם Premium</PRODUCT_NAME>
      <MODEL>נורה ראשית</MODEL>
      <DETAILS>&amp;#9679     H112258PRC1.&amp;#9679  55W  12V  P145s.&amp;#9679 30%   .&amp;#9679         .&amp;#9679     UV.&amp;#9679   3200K.&amp;#9679   1690lm.&amp;#9679   400 .&amp;#9679  Philips  Premium.&amp;#9679   .  </DETAILS>
      <CATALOG_NUMBER>616</CATALOG_NUMBER>
      <CURRENCY>ILS</CURRENCY>
      <PRICE>25</PRICE>
      <SHIPMENT_COST>14</SHIPMENT_COST>
      <DELIVERY_TIME>9</DELIVERY_TIME>
      <MANUFACTURER>Philips Car Lights</MANUFACTURER>
      <WARRANTY>-</WARRANTY>
      <IMAGE>http://www.migvanhome.co.il/images/prudact/Philips.headlighting.lamp.H1.12V.55W.P14.5s.Blister_Main.Image.jpg</IMAGE>
      <TAX>1</TAX>
    </PRODUCT>
    <PRODUCT>
      <PRODUCT_URL>http://www.migvanhome.co.il/product.php?pid=617</PRODUCT_URL>
      <PRODUCT_NAME>נורה ראשית לרכב H4 תוצרת Philips דגם Premium</PRODUCT_NAME>
      <MODEL>נורה ראשית</MODEL>
      <DETAILS>&amp;#9679     H412342PRC1.&amp;#9679  5560W  12V  P43t38..&amp;#9679 30%   .&amp;#9679         .&amp;#9679     UV.&amp;#9679   3200K.&amp;#9679   1815lm.&amp;#9679   550 .&amp;#9679  Philips  Premium.&amp;#9679   .  </DETAILS>
      <CATALOG_NUMBER>617</CATALOG_NUMBER>
      <CURRENCY>ILS</CURRENCY>
      <PRICE>29</PRICE>
      <SHIPMENT_COST>14</SHIPMENT_COST>
      <DELIVERY_TIME>9</DELIVERY_TIME>
      <MANUFACTURER>Philips Car Lights</MANUFACTURER>
      <WARRANTY>-</WARRANTY>
      <IMAGE>http://www.migvanhome.co.il/images/prudact/Philips.headlighting.lamp.H4.12V.60.55W.P43t-38.Blister_Main.Image.jpg</IMAGE>
      <TAX>1</TAX>
    </PRODUCT>
    <PRODUCT>
      <PRODUCT_URL>http://www.migvanhome.co.il/product.php?pid=618</PRODUCT_URL>
      <PRODUCT_NAME>נורה ראשית לרכב H7 תוצרת Philips דגם Premium</PRODUCT_NAME>
      <MODEL>נורה ראשית</MODEL>
      <DETAILS>&amp;#9679     H712972PRC1.&amp;#9679  55W  12V  PX26d.&amp;#9679 30%   .&amp;#9679         .&amp;#9679     UV.&amp;#9679   3200K.&amp;#9679   1500lm.&amp;#9679   550 .&amp;#9679  Philips  Premium.&amp;#9679   .  </DETAILS>
      <CATALOG_NUMBER>618</CATALOG_NUMBER>
      <CURRENCY>ILS</CURRENCY>
      <PRICE>32</PRICE>
      <SHIPMENT_COST>14</SHIPMENT_COST>
      <DELIVERY_TIME>9</DELIVERY_TIME>
      <MANUFACTURER>Philips Car Lights</MANUFACTURER>
      <WARRANTY>-</WARRANTY>
      <IMAGE>http://www.migvanhome.co.il/images/prudact/Philips.headlighting.lamp.H7.12V.55W.PX26d.Blister_Main.Image.jpg</IMAGE>
      <TAX>1</TAX>
    </PRODUCT>
    <PRODUCT>
      <PRODUCT_URL>http://www.migvanhome.co.il/product.php?pid=619</PRODUCT_URL>
      <PRODUCT_NAME>נורה ראשית לרכב H11 תוצרת Philips דגם Premium</PRODUCT_NAME>
      <MODEL>נורה ראשית</MODEL>
      <DETAILS>&amp;#9679     H11.&amp;#9679  55W  12V  PGJ192.&amp;#9679 30%   .&amp;#9679         .&amp;#9679     UV.&amp;#9679   3200K.&amp;#9679   1350lm.&amp;#9679   800 .&amp;#9679  Philips  Premium.&amp;#9679   .  </DETAILS>
      <CATALOG_NUMBER>619</CATALOG_NUMBER>
      <CURRENCY>ILS</CURRENCY>
      <PRICE>55</PRICE>
      <SHIPMENT_COST>14</SHIPMENT_COST>
      <DELIVERY_TIME>9</DELIVERY_TIME>
      <MANUFACTURER>Philips Car Lights</MANUFACTURER>
      <WARRANTY>-</WARRANTY>
      <IMAGE>http://www.migvanhome.co.il/images/prudact/Philips.headlighting.lamp.H11.55W.jpg</IMAGE>
      <TAX>1</TAX>
    </PRODUCT>
    <PRODUCT>
      <PRODUCT_URL>http://www.migvanhome.co.il/product.php?pid=620</PRODUCT_URL>
      <PRODUCT_NAME>נורה ראשית לרכב HB3 תוצרת Philips דגם Premium</PRODUCT_NAME>
      <MODEL>נורה ראשית</MODEL>
      <DETAILS>&amp;#9679     HB39005.&amp;#9679  65W  12V  P20d.&amp;#9679 30%   .&amp;#9679         .&amp;#9679     UV.&amp;#9679    3200K.&amp;#9679   1860lm.&amp;#9679   300 .&amp;#9679  Philips  Premium.&amp;#9679   .  </DETAILS>
      <CATALOG_NUMBER>620</CATALOG_NUMBER>
      <CURRENCY>ILS</CURRENCY>
      <PRICE>35</PRICE>
      <SHIPMENT_COST>14</SHIPMENT_COST>
      <DELIVERY_TIME>9</DELIVERY_TIME>
      <MANUFACTURER>Philips Car Lights</MANUFACTURER>
      <WARRANTY>-</WARRANTY>
      <IMAGE>http://www.migvanhome.co.il/images/prudact/Philips.headlighting.lamp.HB3.65W.jpg</IMAGE>
      <TAX>1</TAX>
    </PRODUCT>
    <PRODUCT>
      <PRODUCT_URL>http://www.migvanhome.co.il/product.php?pid=621</PRODUCT_URL>
      <PRODUCT_NAME>נורה ראשית לרכב HB4 תוצרת Philips דגם Premium</PRODUCT_NAME>
      <MODEL>נורה ראשית</MODEL>
      <DETAILS>&amp;#9679     HB49006.&amp;#9679  55W  12V  P22d.&amp;#9679 30%   .&amp;#9679         .&amp;#9679     UV.&amp;#9679    3200K.&amp;#9679   1095lm.&amp;#9679   980 .&amp;#9679  Philips  Premium.&amp;#9679   .  </DETAILS>
      <CATALOG_NUMBER>621</CATALOG_NUMBER>
      <CURRENCY>ILS</CURRENCY>
      <PRICE>35</PRICE>
      <SHIPMENT_COST>14</SHIPMENT_COST>
      <DELIVERY_TIME>9</DELIVERY_TIME>
      <MANUFACTURER>Philips Car Lights</MANUFACTURER>
      <WARRANTY>-</WARRANTY>
      <IMAGE>http://www.migvanhome.co.il/images/prudact/Philips.headlighting.lamp.HB4.12V.55W.P22d.Blister_Main.Image.jpg</IMAGE>
      <TAX>1</TAX>
    </PRODUCT>
    <PRODUCT>
      <PRODUCT_URL>http://www.migvanhome.co.il/product.php?pid=622</PRODUCT_URL>
      <PRODUCT_NAME>נורה ראשית לרכב Hir2 תוצרת Philips דגם Longer Life</PRODUCT_NAME>
      <MODEL>נורה ראשית</MODEL>
      <DETAILS>&amp;#9679     9012LL.&amp;#9679  55W  12V  Px22d.&amp;#9679  Longer Life  3    .&amp;#9679         .&amp;#9679     UV.&amp;#9679   3200K.&amp;#9679  Philips  Longer Life.&amp;#9679   .&amp;#9679       20122015    Limited   2014     20112014   ix35  20102015   108  20152016</DETAILS>
      <CATALOG_NUMBER>622</CATALOG_NUMBER>
      <CURRENCY>ILS</CURRENCY>
      <PRICE>185</PRICE>
      <SHIPMENT_COST>14</SHIPMENT_COST>
      <DELIVERY_TIME>9</DELIVERY_TIME>
      <MANUFACTURER>Philips Car Lights</MANUFACTURER>
      <WARRANTY>-</WARRANTY>
      <IMAGE>http://www.migvanhome.co.il/images/prudact/Philips.headlighting.lamp.9012.12V.55W.PX22d_Main.Image.jpg</IMAGE>
      <TAX>1</TAX>
    </PRODUCT>
    <PRODUCT>
      <PRODUCT_URL>http://www.migvanhome.co.il/product.php?pid=645</PRODUCT_URL>
      <PRODUCT_NAME>סט מנורות לרכב NOVA דגם H4</PRODUCT_NAME>
      <MODEL>סט מנורות לרכב</MODEL>
      <DETAILS>&amp;#9679    12V  .&amp;#9679  H4 12V 6055W P43T.&amp;#9679   S25 12V 21W BA15S.&amp;#9679   S25 12V 215W BAY15D.&amp;#9679   G18 12V 5W BA15S.&amp;#9679   T10 12V 5W WEDGE.&amp;#9679  ATC 20A.&amp;#9679  ATC 25A.&amp;#9679  NOVA  H4.</DETAILS>
      <CATALOG_NUMBER>645</CATALOG_NUMBER>
      <CURRENCY>ILS</CURRENCY>
      <PRICE>25</PRICE>
      <SHIPMENT_COST>14</SHIPMENT_COST>
      <DELIVERY_TIME>9</DELIVERY_TIME>
      <MANUFACTURER>NOVA</MANUFACTURER>
      <WARRANTY>-</WARRANTY>
      <IMAGE>http://www.migvanhome.co.il/images/prudact/Bulb.Kit.H4.NOVA.jpg</IMAGE>
      <TAX>1</TAX>
    </PRODUCT>
    <PRODUCT>
      <PRODUCT_URL>http://www.migvanhome.co.il/product.php?pid=646</PRODUCT_URL>
      <PRODUCT_NAME>סט מנורות לרכב NOVA דגם H7</PRODUCT_NAME>
      <MODEL>סט מנורות</MODEL>
      <DETAILS>&amp;#9679    12V  .&amp;#9679  H7 12V 55W PX26D.&amp;#9679   S25 12V 21W BA15S.&amp;#9679   S25 12V 215W BAY15D.&amp;#9679   G18 12V 5W BA15S.&amp;#9679   T10 12V 5W WEDGE.&amp;#9679  ATC 20A.&amp;#9679  ATC 25A.&amp;#9679  NOVA  H7.</DETAILS>
      <CATALOG_NUMBER>646</CATALOG_NUMBER>
      <CURRENCY>ILS</CURRENCY>
      <PRICE>25</PRICE>
      <SHIPMENT_COST>14</SHIPMENT_COST>
      <DELIVERY_TIME>9</DELIVERY_TIME>
      <MANUFACTURER>NOVA</MANUFACTURER>
      <WARRANTY>-</WARRANTY>
      <IMAGE>http://www.migvanhome.co.il/images/prudact/Bulb.Kit.H7.NOVA.jpg</IMAGE>
      <TAX>1</TAX>
    </PRODUCT>
    <PRODUCT>
      <PRODUCT_URL>http://www.migvanhome.co.il/product.php?pid=767</PRODUCT_URL>
      <PRODUCT_NAME>זוג נורות ראשיות לרכב H1 תוצרת Philips דגם White Vision</PRODUCT_NAME>
      <MODEL>נורה ראשית</MODEL>
      <DETAILS>&amp;#9679      H1     W5W.&amp;#9679  55W   12V  P145s.&amp;#9679  .&amp;#9679 60%   .&amp;#9679   4300K.&amp;#9679         .&amp;#9679     UV.&amp;#9679    Philips    .&amp;#9679  Philips  WhiteVision.  </DETAILS>
      <CATALOG_NUMBER>767</CATALOG_NUMBER>
      <CURRENCY>ILS</CURRENCY>
      <PRICE>129</PRICE>
      <SHIPMENT_COST>14</SHIPMENT_COST>
      <DELIVERY_TIME>9</DELIVERY_TIME>
      <MANUFACTURER>Philips Car Lights</MANUFACTURER>
      <WARRANTY>-</WARRANTY>
      <IMAGE>http://www.migvanhome.co.il/images/prudact/Philips.headlighting.lamp.H1.WhiteVision.jpg</IMAGE>
      <TAX>1</TAX>
    </PRODUCT>
    <PRODUCT>
      <PRODUCT_URL>http://www.migvanhome.co.il/product.php?pid=768</PRODUCT_URL>
      <PRODUCT_NAME>נורה ראשית לרכב H3 תוצרת Philips דגם Premium</PRODUCT_NAME>
      <MODEL>נורה ראשית</MODEL>
      <DETAILS>&amp;#9679    H3.&amp;#9679  55W   12V.&amp;#9679 30%   .&amp;#9679         .&amp;#9679     UV.&amp;#9679   .&amp;#9679  Philips  Premium.&amp;#9679   .  </DETAILS>
      <CATALOG_NUMBER>768</CATALOG_NUMBER>
      <CURRENCY>ILS</CURRENCY>
      <PRICE>22</PRICE>
      <SHIPMENT_COST>14</SHIPMENT_COST>
      <DELIVERY_TIME>9</DELIVERY_TIME>
      <MANUFACTURER>Philips Car Lights</MANUFACTURER>
      <WARRANTY>-</WARRANTY>
      <IMAGE>http://www.migvanhome.co.il/images/prudact/Philips.headlighting.lamp.H3.12V.55W_Main.Image.jpg</IMAGE>
      <TAX>1</TAX>
    </PRODUCT>
    <PRODUCT>
      <PRODUCT_URL>http://www.migvanhome.co.il/product.php?pid=769</PRODUCT_URL>
      <PRODUCT_NAME>זוג נורות ראשיות לרכב H7 תוצרת Philips דגם X-tremeVision</PRODUCT_NAME>
      <MODEL>נורה ראשית</MODEL>
      <DETAILS>&amp;#9679    H7.&amp;#9679  55W   12V.&amp;#9679 130%   .&amp;#9679   3700K.&amp;#9679         .&amp;#9679     UV.&amp;#9679    Philips    .&amp;#9679  Philips  XtremeVision.&amp;#9679   .  </DETAILS>
      <CATALOG_NUMBER>769</CATALOG_NUMBER>
      <CURRENCY>ILS</CURRENCY>
      <PRICE>175</PRICE>
      <SHIPMENT_COST>14</SHIPMENT_COST>
      <DELIVERY_TIME>9</DELIVERY_TIME>
      <MANUFACTURER>Philips Car Lights</MANUFACTURER>
      <WARRANTY>-</WARRANTY>
      <IMAGE>http://www.migvanhome.co.il/images/prudact/Philips.headlighting.lamp.H7.X-tremeVision_Main.Image.jpg</IMAGE>
      <TAX>1</TAX>
    </PRODUCT>
    <PRODUCT>
      <PRODUCT_URL>http://www.migvanhome.co.il/product.php?pid=770</PRODUCT_URL>
      <PRODUCT_NAME>זוג נורות ראשיות לרכב H4 תוצרת Philips דגם White Vision</PRODUCT_NAME>
      <MODEL>נורה ראשית</MODEL>
      <DETAILS>&amp;#9679      H4     W5W.&amp;#9679  6055W   12V  P145s.&amp;#9679  .&amp;#9679 60%   .&amp;#9679   4300K.&amp;#9679         .&amp;#9679     UV.&amp;#9679    Philips    .&amp;#9679  Philips  White Vision.&amp;#9679   .  </DETAILS>
      <CATALOG_NUMBER>770</CATALOG_NUMBER>
      <CURRENCY>ILS</CURRENCY>
      <PRICE>139</PRICE>
      <SHIPMENT_COST>14</SHIPMENT_COST>
      <DELIVERY_TIME>9</DELIVERY_TIME>
      <MANUFACTURER>Philips Car Lights</MANUFACTURER>
      <WARRANTY>-</WARRANTY>
      <IMAGE>http://www.migvanhome.co.il/images/prudact/Philips.headlighting.lamp.H4.White.Vision.jpg</IMAGE>
      <TAX>1</TAX>
    </PRODUCT>
    <PRODUCT>
      <PRODUCT_URL>http://www.migvanhome.co.il/product.php?pid=771</PRODUCT_URL>
      <PRODUCT_NAME>זוג נורות ראשיות לרכב H7 תוצרת Philips דגם White Vision</PRODUCT_NAME>
      <MODEL>נורה ראשית</MODEL>
      <DETAILS>&amp;#9679      H7     W5W.&amp;#9679  55W   12V  P145s.&amp;#9679  .&amp;#9679 60%   .&amp;#9679   4300K.&amp;#9679         .&amp;#9679     UV.&amp;#9679    Philips    .&amp;#9679  Philips  White Vision.&amp;#9679   .  </DETAILS>
      <CATALOG_NUMBER>771</CATALOG_NUMBER>
      <CURRENCY>ILS</CURRENCY>
      <PRICE>175</PRICE>
      <SHIPMENT_COST>14</SHIPMENT_COST>
      <DELIVERY_TIME>9</DELIVERY_TIME>
      <MANUFACTURER>Philips Car Lights</MANUFACTURER>
      <WARRANTY>-</WARRANTY>
      <IMAGE>http://www.migvanhome.co.il/images/prudact/Philips.headlighting.lamp.H7.White.Vision_Main.Image.jpg</IMAGE>
      <TAX>1</TAX>
    </PRODUCT>
    <PRODUCT>
      <PRODUCT_URL>http://www.migvanhome.co.il/product.php?pid=772</PRODUCT_URL>
      <PRODUCT_NAME>נורה ראשית לרכב H11 תוצרת Philips דגם White Vision</PRODUCT_NAME>
      <MODEL>נורה ראשית</MODEL>
      <DETAILS>&amp;#9679    H11.&amp;#9679  55W   12V.&amp;#9679  .&amp;#9679 60%   .&amp;#9679   3600K.&amp;#9679         .&amp;#9679     UV.&amp;#9679    Philips    .&amp;#9679  Philips  White Vision.&amp;#9679   .  </DETAILS>
      <CATALOG_NUMBER>772</CATALOG_NUMBER>
      <CURRENCY>ILS</CURRENCY>
      <PRICE>95</PRICE>
      <SHIPMENT_COST>14</SHIPMENT_COST>
      <DELIVERY_TIME>9</DELIVERY_TIME>
      <MANUFACTURER>Philips Car Lights</MANUFACTURER>
      <WARRANTY>-</WARRANTY>
      <IMAGE>http://www.migvanhome.co.il/images/prudact/Philips.headlighting.lamp.H11.WhiteVision.jpg</IMAGE>
      <TAX>1</TAX>
    </PRODUCT>
    <PRODUCT>
      <PRODUCT_URL>http://www.migvanhome.co.il/product.php?pid=773</PRODUCT_URL>
      <PRODUCT_NAME>זוג נורות בלם לרכב מגע אחד Philips דגם P21W</PRODUCT_NAME>
      <MODEL>נורת בלם</MODEL>
      <DETAILS>&amp;#9679      .&amp;#9679  21W   12V.&amp;#9679  Philips  Vision.&amp;#9679   .  </DETAILS>
      <CATALOG_NUMBER>773</CATALOG_NUMBER>
      <CURRENCY>ILS</CURRENCY>
      <PRICE>12</PRICE>
      <SHIPMENT_COST>14</SHIPMENT_COST>
      <DELIVERY_TIME>9</DELIVERY_TIME>
      <MANUFACTURER>Philips Car Lights</MANUFACTURER>
      <WARRANTY>-</WARRANTY>
      <IMAGE>http://www.migvanhome.co.il/images/prudact/Brake.light.Single.Contacts.Philips.P21W_Main.Image.jpg</IMAGE>
      <TAX>1</TAX>
    </PRODUCT>
    <PRODUCT>
      <PRODUCT_URL>http://www.migvanhome.co.il/product.php?pid=774</PRODUCT_URL>
      <PRODUCT_NAME>זוג נורות בלם לרכב שני מגעים Philips דגם P21/5W</PRODUCT_NAME>
      <MODEL>נורת בלם</MODEL>
      <DETAILS>&amp;#9679      P215W.&amp;#9679  521W   12V.&amp;#9679   440lm.&amp;#9679   250 .&amp;#9679  Philips  Vision.&amp;#9679   .  </DETAILS>
      <CATALOG_NUMBER>774</CATALOG_NUMBER>
      <CURRENCY>ILS</CURRENCY>
      <PRICE>14</PRICE>
      <SHIPMENT_COST>14</SHIPMENT_COST>
      <DELIVERY_TIME>9</DELIVERY_TIME>
      <MANUFACTURER>Philips Car Lights</MANUFACTURER>
      <WARRANTY>-</WARRANTY>
      <IMAGE>http://www.migvanhome.co.il/images/prudact/Brake.light.Dual.Contacts.Philips.P21.5W_Main.Image.jpg</IMAGE>
      <TAX>1</TAX>
    </PRODUCT>
    <PRODUCT>
      <PRODUCT_URL>http://www.migvanhome.co.il/product.php?pid=795</PRODUCT_URL>
      <PRODUCT_NAME>נורת בננה לרכב 10 יח'  Philips דגם C5W</PRODUCT_NAME>
      <MODEL>נורת לוחית רישוי</MODEL>
      <DETAILS>&amp;#9679   .&amp;#9679  5W  12V.&amp;#9679  35 .&amp;#9679    ...&amp;#9679 10  .&amp;#9679  Philips  .  12844CP.&amp;#9679   .  </DETAILS>
      <CATALOG_NUMBER>795</CATALOG_NUMBER>
      <CURRENCY>ILS</CURRENCY>
      <PRICE>25</PRICE>
      <SHIPMENT_COST>14</SHIPMENT_COST>
      <DELIVERY_TIME>9</DELIVERY_TIME>
      <MANUFACTURER>Philips Car Lights</MANUFACTURER>
      <WARRANTY>-</WARRANTY>
      <IMAGE>http://www.migvanhome.co.il/images/prudact/Philips.C5W.10pcs_Main.Image.jpg</IMAGE>
      <TAX>1</TAX>
    </PRODUCT>
    <PRODUCT>
      <PRODUCT_URL>http://www.migvanhome.co.il/product.php?pid=796</PRODUCT_URL>
      <PRODUCT_NAME>נורת בלם לרכב 10 יח' Philips דגם P21/4W</PRODUCT_NAME>
      <MODEL>נורת בלם</MODEL>
      <DETAILS>&amp;#9679      .&amp;#9679  214W  12V  BAZ15d.&amp;#9679   440lm.&amp;#9679   250 .&amp;#9679 10  .&amp;#9679  Philips  .  12594CP.&amp;#9679   .  </DETAILS>
      <CATALOG_NUMBER>796</CATALOG_NUMBER>
      <CURRENCY>ILS</CURRENCY>
      <PRICE>45</PRICE>
      <SHIPMENT_COST>14</SHIPMENT_COST>
      <DELIVERY_TIME>9</DELIVERY_TIME>
      <MANUFACTURER>Philips Car Lights</MANUFACTURER>
      <WARRANTY>-</WARRANTY>
      <IMAGE>http://www.migvanhome.co.il/images/prudact/Philips.P21.4W.10pcs_Main.Image.jpg</IMAGE>
      <TAX>1</TAX>
    </PRODUCT>
    <PRODUCT>
      <PRODUCT_URL>http://www.migvanhome.co.il/product.php?pid=797</PRODUCT_URL>
      <PRODUCT_NAME>נורת בלם לרכב 10 יח' Philips דגם P21/5W</PRODUCT_NAME>
      <MODEL>נורת בלם</MODEL>
      <DETAILS>&amp;#9679     .&amp;#9679  215W  12V  BAY15d.&amp;#9679   440lm.&amp;#9679   250 .&amp;#9679 10  .&amp;#9679  Philips  .  12499CP.&amp;#9679   .  </DETAILS>
      <CATALOG_NUMBER>797</CATALOG_NUMBER>
      <CURRENCY>ILS</CURRENCY>
      <PRICE>29</PRICE>
      <SHIPMENT_COST>14</SHIPMENT_COST>
      <DELIVERY_TIME>9</DELIVERY_TIME>
      <MANUFACTURER>Philips Car Lights</MANUFACTURER>
      <WARRANTY>-</WARRANTY>
      <IMAGE>http://www.migvanhome.co.il/images/prudact/Philips.P21.5W.10pcs_Main.Image.jpg</IMAGE>
      <TAX>1</TAX>
    </PRODUCT>
    <PRODUCT>
      <PRODUCT_URL>http://www.migvanhome.co.il/product.php?pid=798</PRODUCT_URL>
      <PRODUCT_NAME>נורת בלם לרכב 10 יח' Philips דגם P21W</PRODUCT_NAME>
      <MODEL>נורת בלם</MODEL>
      <DETAILS>&amp;#9679     .&amp;#9679  21W  12V.&amp;#9679      ...&amp;#9679 10  .&amp;#9679  Philips  .  12498CP.&amp;#9679   .  </DETAILS>
      <CATALOG_NUMBER>798</CATALOG_NUMBER>
      <CURRENCY>ILS</CURRENCY>
      <PRICE>28</PRICE>
      <SHIPMENT_COST>14</SHIPMENT_COST>
      <DELIVERY_TIME>9</DELIVERY_TIME>
      <MANUFACTURER>Philips Car Lights</MANUFACTURER>
      <WARRANTY>-</WARRANTY>
      <IMAGE>http://www.migvanhome.co.il/images/prudact/Philips.P21W.10pcs_Main.Image.jpg</IMAGE>
      <TAX>1</TAX>
    </PRODUCT>
    <PRODUCT>
      <PRODUCT_URL>http://www.migvanhome.co.il/product.php?pid=799</PRODUCT_URL>
      <PRODUCT_NAME>נורת וינקר לרכב 10 יח' Philips דגם PY21W</PRODUCT_NAME>
      <MODEL>נורת וינקר</MODEL>
      <DETAILS>&amp;#9679     .&amp;#9679  21W  12V  BAU15s.&amp;#9679 10  .&amp;#9679   280lm.&amp;#9679   500 .&amp;#9679  Philips  .  12496NACP.&amp;#9679   .  </DETAILS>
      <CATALOG_NUMBER>799</CATALOG_NUMBER>
      <CURRENCY>ILS</CURRENCY>
      <PRICE>49</PRICE>
      <SHIPMENT_COST>14</SHIPMENT_COST>
      <DELIVERY_TIME>9</DELIVERY_TIME>
      <MANUFACTURER>Philips Car Lights</MANUFACTURER>
      <WARRANTY>-</WARRANTY>
      <IMAGE>http://www.migvanhome.co.il/images/prudact/Philips.PY21W.10pcs_Main.Image.jpg</IMAGE>
      <TAX>1</TAX>
    </PRODUCT>
    <PRODUCT>
      <PRODUCT_URL>http://www.migvanhome.co.il/product.php?pid=800</PRODUCT_URL>
      <PRODUCT_NAME>נורת בלם לרכב 10 יח'  Philips דגם R5W</PRODUCT_NAME>
      <MODEL>נורת בלם</MODEL>
      <DETAILS>&amp;#9679   .&amp;#9679  5W  12V  BA15s.&amp;#9679   50lm.&amp;#9679   625 .&amp;#9679 10  .&amp;#9679  Philips  .  12821CP.&amp;#9679   .  </DETAILS>
      <CATALOG_NUMBER>800</CATALOG_NUMBER>
      <CURRENCY>ILS</CURRENCY>
      <PRICE>28</PRICE>
      <SHIPMENT_COST>14</SHIPMENT_COST>
      <DELIVERY_TIME>9</DELIVERY_TIME>
      <MANUFACTURER>Philips Car Lights</MANUFACTURER>
      <WARRANTY>-</WARRANTY>
      <IMAGE>http://www.migvanhome.co.il/images/prudact/Philips.R5W.10pcs_Main.Image.jpg</IMAGE>
      <TAX>1</TAX>
    </PRODUCT>
    <PRODUCT>
      <PRODUCT_URL>http://www.migvanhome.co.il/product.php?pid=801</PRODUCT_URL>
      <PRODUCT_NAME>נורת חניה לרכב 10 יח' Philips דגם W5W</PRODUCT_NAME>
      <MODEL>נורת חניה</MODEL>
      <DETAILS>&amp;#9679     .&amp;#9679  5W  12V.&amp;#9679       ...&amp;#9679   50lm.&amp;#9679   1500 .&amp;#9679 10  .&amp;#9679  Philips  .  12961CP.&amp;#9679   .  </DETAILS>
      <CATALOG_NUMBER>801</CATALOG_NUMBER>
      <CURRENCY>ILS</CURRENCY>
      <PRICE>18</PRICE>
      <SHIPMENT_COST>14</SHIPMENT_COST>
      <DELIVERY_TIME>9</DELIVERY_TIME>
      <MANUFACTURER>Philips Car Lights</MANUFACTURER>
      <WARRANTY>-</WARRANTY>
      <IMAGE>http://www.migvanhome.co.il/images/prudact/Philips.W5W.10pcs_Main.Image.jpg</IMAGE>
      <TAX>1</TAX>
    </PRODUCT>
    <PRODUCT>
      <PRODUCT_URL>http://www.migvanhome.co.il/product.php?pid=802</PRODUCT_URL>
      <PRODUCT_NAME>נורת חניה לרכב 10 יח' Philips דגם W16W</PRODUCT_NAME>
      <MODEL>נורת חניה</MODEL>
      <DETAILS>&amp;#9679     .&amp;#9679  16W  12V  BAU15s.&amp;#9679   310lm.&amp;#9679   700 .&amp;#9679      ...&amp;#9679 10  .&amp;#9679  Philips  .  12067CP.&amp;#9679   .  </DETAILS>
      <CATALOG_NUMBER>802</CATALOG_NUMBER>
      <CURRENCY>ILS</CURRENCY>
      <PRICE>69</PRICE>
      <SHIPMENT_COST>14</SHIPMENT_COST>
      <DELIVERY_TIME>9</DELIVERY_TIME>
      <MANUFACTURER>Philips Car Lights</MANUFACTURER>
      <WARRANTY>-</WARRANTY>
      <IMAGE>http://www.migvanhome.co.il/images/prudact/Philips.W16W.10pcs_Main.Image.jpg</IMAGE>
      <TAX>1</TAX>
    </PRODUCT>
    <PRODUCT>
      <PRODUCT_URL>http://www.migvanhome.co.il/product.php?pid=907</PRODUCT_URL>
      <PRODUCT_NAME>זוג נורות חניה Philips דגם W5W</PRODUCT_NAME>
      <MODEL>W5W</MODEL>
      <DETAILS>&amp;#9679     W5W.&amp;#9679  5W  12V.&amp;#9679   50lm.&amp;#9679   1500 .&amp;#9679      ..&amp;#9679 2  .&amp;#9679  Philips  .  12961B2.&amp;#9679   .  </DETAILS>
      <CATALOG_NUMBER>907</CATALOG_NUMBER>
      <CURRENCY>ILS</CURRENCY>
      <PRICE>9</PRICE>
      <SHIPMENT_COST>14</SHIPMENT_COST>
      <DELIVERY_TIME>9</DELIVERY_TIME>
      <MANUFACTURER>Philips Car Lights</MANUFACTURER>
      <WARRANTY>-</WARRANTY>
      <IMAGE>http://www.migvanhome.co.il/images/prudact/Philips.Dual.Brake.bulbs.W5W_Main.Image.jpg</IMAGE>
      <TAX>1</TAX>
    </PRODUCT>
    <PRODUCT>
      <PRODUCT_URL>http://www.migvanhome.co.il/product.php?pid=931</PRODUCT_URL>
      <PRODUCT_NAME>זוג נורות איתות Philips דגם PY21W</PRODUCT_NAME>
      <MODEL>PY21W</MODEL>
      <DETAILS>&amp;#9679    PY21W.&amp;#9679  21W  12V.&amp;#9679   280lm.&amp;#9679   500 .&amp;#9679    &amp;#9679 2  .&amp;#9679  Philips  .  12496NAB2.&amp;#9679   .  </DETAILS>
      <CATALOG_NUMBER>931</CATALOG_NUMBER>
      <CURRENCY>ILS</CURRENCY>
      <PRICE>18</PRICE>
      <SHIPMENT_COST>14</SHIPMENT_COST>
      <DELIVERY_TIME>9</DELIVERY_TIME>
      <MANUFACTURER>Philips Car Lights</MANUFACTURER>
      <WARRANTY>-</WARRANTY>
      <IMAGE>http://www.migvanhome.co.il/images/prudact/Philips.Dual.Brake.bulbs.PY21W_Main.Image.jpg</IMAGE>
      <TAX>1</TAX>
    </PRODUCT>
    <PRODUCT>
      <PRODUCT_URL>http://www.migvanhome.co.il/product.php?pid=939</PRODUCT_URL>
      <PRODUCT_NAME>נורה ראשית לרכב Tungsram דגם H8</PRODUCT_NAME>
      <MODEL>H8</MODEL>
      <DETAILS>&amp;#9679    H8.&amp;#9679  35W  12V.&amp;#9679     UV.&amp;#9679     .&amp;#9679  Tungsram  H8&amp;#9679    H8       i10  20142015    308  20142015    508  20082013</DETAILS>
      <CATALOG_NUMBER>939</CATALOG_NUMBER>
      <CURRENCY>ILS</CURRENCY>
      <PRICE>39</PRICE>
      <SHIPMENT_COST>14</SHIPMENT_COST>
      <DELIVERY_TIME>9</DELIVERY_TIME>
      <MANUFACTURER>Tungsram</MANUFACTURER>
      <WARRANTY>-</WARRANTY>
      <IMAGE>http://www.migvanhome.co.il/images/prudact/Tungsram.H8.35W_Main.Image.jpg</IMAGE>
      <TAX>1</TAX>
    </PRODUCT>
    <PRODUCT>
      <PRODUCT_URL>http://www.migvanhome.co.il/product.php?pid=940</PRODUCT_URL>
      <PRODUCT_NAME>נורת חניה הלוגן General Electric דגם H6W</PRODUCT_NAME>
      <MODEL>H6W</MODEL>
      <DETAILS>&amp;#9679    .&amp;#9679  6W  12V.&amp;#9679      H6W.&amp;#9679   .  </DETAILS>
      <CATALOG_NUMBER>940</CATALOG_NUMBER>
      <CURRENCY>ILS</CURRENCY>
      <PRICE>14</PRICE>
      <SHIPMENT_COST>14</SHIPMENT_COST>
      <DELIVERY_TIME>9</DELIVERY_TIME>
      <MANUFACTURER>General Electric</MANUFACTURER>
      <WARRANTY>-</WARRANTY>
      <IMAGE>http://www.migvanhome.co.il/images/prudact/Bulb.Parking.H6W.jpg</IMAGE>
      <TAX>1</TAX>
    </PRODUCT>
    <PRODUCT>
      <PRODUCT_URL>http://www.migvanhome.co.il/product.php?pid=958</PRODUCT_URL>
      <PRODUCT_NAME>נורת בננה לרכב 10 יח' philips LongLife דגם C10W</PRODUCT_NAME>
      <MODEL/>
      <DETAILS>&amp;#9679    C10W.&amp;#9679  10W  12V.&amp;#9679   125lm.&amp;#9679   625 .&amp;#9679      ...&amp;#9679 10  .&amp;#9679  Philips  .  12860LLECOCP.&amp;#9679   .  </DETAILS>
      <CATALOG_NUMBER>958</CATALOG_NUMBER>
      <CURRENCY>ILS</CURRENCY>
      <PRICE>75</PRICE>
      <SHIPMENT_COST>14</SHIPMENT_COST>
      <DELIVERY_TIME>9</DELIVERY_TIME>
      <MANUFACTURER>Philips Car Lights</MANUFACTURER>
      <WARRANTY>-</WARRANTY>
      <IMAGE>http://www.migvanhome.co.il/images/prudact/Philips.LongLife.C10W.10pcs_Main.Image.jpg</IMAGE>
      <TAX>1</TAX>
    </PRODUCT>
    <PRODUCT>
      <PRODUCT_URL>http://www.migvanhome.co.il/product.php?pid=959</PRODUCT_URL>
      <PRODUCT_NAME>נורה ראשית לרכב Tungsram דגם H9</PRODUCT_NAME>
      <MODEL>H9</MODEL>
      <DETAILS>&amp;#9679    H9.&amp;#9679  65W  12V.&amp;#9679     UV.&amp;#9679      .&amp;#9679  Tungsram  H9&amp;#9679   </DETAILS>
      <CATALOG_NUMBER>959</CATALOG_NUMBER>
      <CURRENCY>ILS</CURRENCY>
      <PRICE>39</PRICE>
      <SHIPMENT_COST>14</SHIPMENT_COST>
      <DELIVERY_TIME>9</DELIVERY_TIME>
      <MANUFACTURER>Tungsram</MANUFACTURER>
      <WARRANTY>-</WARRANTY>
      <IMAGE>http://www.migvanhome.co.il/images/prudact/Tungsram.H9.65W_Main.Image.jpg</IMAGE>
      <TAX>1</TAX>
    </PRODUCT>
    <PRODUCT>
      <PRODUCT_URL>http://www.migvanhome.co.il/product.php?pid=960</PRODUCT_URL>
      <PRODUCT_NAME>נורת ערפל אחורי לרכב 10 יח' philips דגם PR21W</PRODUCT_NAME>
      <MODEL/>
      <DETAILS>&amp;#9679    PR21W.&amp;#9679  21W  12V.&amp;#9679   110lm.&amp;#9679   600 .&amp;#9679    ...&amp;#9679 10  .&amp;#9679  Philips  .  12088CP.&amp;#9679   .   PR21W       C3  20102015    C3  20082015</DETAILS>
      <CATALOG_NUMBER>960</CATALOG_NUMBER>
      <CURRENCY>ILS</CURRENCY>
      <PRICE>129</PRICE>
      <SHIPMENT_COST>14</SHIPMENT_COST>
      <DELIVERY_TIME>9</DELIVERY_TIME>
      <MANUFACTURER>Philips Car Lights</MANUFACTURER>
      <WARRANTY>-</WARRANTY>
      <IMAGE>http://www.migvanhome.co.il/images/prudact/Philips.PR21W.10pcs_Main.Image.jpg</IMAGE>
      <TAX>1</TAX>
    </PRODUCT>
    <PRODUCT>
      <PRODUCT_URL>http://www.migvanhome.co.il/product.php?pid=961</PRODUCT_URL>
      <PRODUCT_NAME>נורה ראשית לרכב Nova דגם H15</PRODUCT_NAME>
      <MODEL>H15</MODEL>
      <DETAILS>&amp;#9679    H15.&amp;#9679  55W  12V.&amp;#9679      .&amp;#9679  Nova  H15 H15      3  20152015   CX5  20132015</DETAILS>
      <CATALOG_NUMBER>961</CATALOG_NUMBER>
      <CURRENCY>ILS</CURRENCY>
      <PRICE>75</PRICE>
      <SHIPMENT_COST>14</SHIPMENT_COST>
      <DELIVERY_TIME>9</DELIVERY_TIME>
      <MANUFACTURER>Nova</MANUFACTURER>
      <WARRANTY>-</WARRANTY>
      <IMAGE>http://www.migvanhome.co.il/images/prudact/Nova.Halogen.Lamp.H15.jpg</IMAGE>
      <TAX>1</TAX>
    </PRODUCT>
    <PRODUCT>
      <PRODUCT_URL>http://www.migvanhome.co.il/product.php?pid=962</PRODUCT_URL>
      <PRODUCT_NAME>נורה לרכב 10 יח' philips דגם R10W</PRODUCT_NAME>
      <MODEL>R10W</MODEL>
      <DETAILS>&amp;#9679   R10W.&amp;#9679  10W  12V.&amp;#9679   125lm.&amp;#9679   625 .&amp;#9679      ...&amp;#9679 10  .&amp;#9679  Philips  .  12814CP.&amp;#9679   .  </DETAILS>
      <CATALOG_NUMBER>962</CATALOG_NUMBER>
      <CURRENCY>ILS</CURRENCY>
      <PRICE>29</PRICE>
      <SHIPMENT_COST>14</SHIPMENT_COST>
      <DELIVERY_TIME>9</DELIVERY_TIME>
      <MANUFACTURER>Philips Car Lights</MANUFACTURER>
      <WARRANTY>-</WARRANTY>
      <IMAGE>http://www.migvanhome.co.il/images/prudact/Philips.R10W.10pcs_Main.Image.jpg</IMAGE>
      <TAX>1</TAX>
    </PRODUCT>
    <PRODUCT>
      <PRODUCT_URL>http://www.migvanhome.co.il/product.php?pid=963</PRODUCT_URL>
      <PRODUCT_NAME>נורת איתות צד לרכב 10 יח' philips דגם WY5W</PRODUCT_NAME>
      <MODEL>WY5W</MODEL>
      <DETAILS>&amp;#9679      WY5W.&amp;#9679  21W  12V.&amp;#9679   30lm.&amp;#9679   3000 .&amp;#9679    ...&amp;#9679 10  .&amp;#9679  Philips  .  12396NACP.&amp;#9679   .  </DETAILS>
      <CATALOG_NUMBER>963</CATALOG_NUMBER>
      <CURRENCY>ILS</CURRENCY>
      <PRICE>55</PRICE>
      <SHIPMENT_COST>14</SHIPMENT_COST>
      <DELIVERY_TIME>9</DELIVERY_TIME>
      <MANUFACTURER>Philips Car Lights</MANUFACTURER>
      <WARRANTY>-</WARRANTY>
      <IMAGE>http://www.migvanhome.co.il/images/prudact/Philips.WY5W.10pcs_Main.Image.jpg</IMAGE>
      <TAX>1</TAX>
    </PRODUCT>
    <PRODUCT>
      <PRODUCT_URL>http://www.migvanhome.co.il/product.php?pid=964</PRODUCT_URL>
      <PRODUCT_NAME>נורת בלם לרכב 10 יח' philips דגם W21W</PRODUCT_NAME>
      <MODEL>W21W</MODEL>
      <DETAILS>&amp;#9679      .&amp;#9679  21W  12V.&amp;#9679   460lm.&amp;#9679   400 .&amp;#9679       ...&amp;#9679 10  .&amp;#9679  Philips  .  12065CP.&amp;#9679   .  </DETAILS>
      <CATALOG_NUMBER>964</CATALOG_NUMBER>
      <CURRENCY>ILS</CURRENCY>
      <PRICE>95</PRICE>
      <SHIPMENT_COST>14</SHIPMENT_COST>
      <DELIVERY_TIME>9</DELIVERY_TIME>
      <MANUFACTURER>Philips Car Lights</MANUFACTURER>
      <WARRANTY>-</WARRANTY>
      <IMAGE>http://www.migvanhome.co.il/images/prudact/Philips.W21W.10pcs_Main.Image.jpg</IMAGE>
      <TAX>1</TAX>
    </PRODUCT>
    <PRODUCT>
      <PRODUCT_URL>http://www.migvanhome.co.il/product.php?pid=965</PRODUCT_URL>
      <PRODUCT_NAME>נורת בלם לרכב 10 יח' philips דגם W21/5W</PRODUCT_NAME>
      <MODEL>W21/5W</MODEL>
      <DETAILS>&amp;#9679       W215W.&amp;#9679  215W  12V.&amp;#9679   440lm.&amp;#9679   400 .&amp;#9679     ...&amp;#9679 10  .&amp;#9679  Philips  .  12066CP.&amp;#9679   .  </DETAILS>
      <CATALOG_NUMBER>965</CATALOG_NUMBER>
      <CURRENCY>ILS</CURRENCY>
      <PRICE>135</PRICE>
      <SHIPMENT_COST>14</SHIPMENT_COST>
      <DELIVERY_TIME>9</DELIVERY_TIME>
      <MANUFACTURER>Philips Car Lights</MANUFACTURER>
      <WARRANTY>-</WARRANTY>
      <IMAGE>http://www.migvanhome.co.il/images/prudact/Philips.W21.5W.10pcs_Main.Image.jpg</IMAGE>
      <TAX>1</TAX>
    </PRODUCT>
    <PRODUCT>
      <PRODUCT_URL>http://www.migvanhome.co.il/product.php?pid=966</PRODUCT_URL>
      <PRODUCT_NAME>נורת ערפל קדמי/אחורי לרכב philips דגם PSX24W</PRODUCT_NAME>
      <MODEL>PSX24W</MODEL>
      <DETAILS>&amp;#9679     PSX24W.&amp;#9679  24W  12V.&amp;#9679   500lm.&amp;#9679   1500 .&amp;#9679    &amp;#9679  Philips  .  12276C1.&amp;#9679   .  </DETAILS>
      <CATALOG_NUMBER>966</CATALOG_NUMBER>
      <CURRENCY>ILS</CURRENCY>
      <PRICE>69</PRICE>
      <SHIPMENT_COST>14</SHIPMENT_COST>
      <DELIVERY_TIME>9</DELIVERY_TIME>
      <MANUFACTURER>Philips Car Lights</MANUFACTURER>
      <WARRANTY>-</WARRANTY>
      <IMAGE>http://www.migvanhome.co.il/images/prudact/Philips.PSX24W_Main.Image.jpg</IMAGE>
      <TAX>1</TAX>
    </PRODUCT>
    <PRODUCT>
      <PRODUCT_URL>http://www.migvanhome.co.il/product.php?pid=967</PRODUCT_URL>
      <PRODUCT_NAME>נורת ערפל קדמי לרכב philips דגם H27W/1 ישר</PRODUCT_NAME>
      <MODEL>H27W/1</MODEL>
      <DETAILS>&amp;#9679     H27W1.&amp;#9679  27W  12V.&amp;#9679   477lm.&amp;#9679   300 .&amp;#9679    &amp;#9679  Philips  .  12059C1.&amp;#9679   .  </DETAILS>
      <CATALOG_NUMBER>967</CATALOG_NUMBER>
      <CURRENCY>ILS</CURRENCY>
      <PRICE>29</PRICE>
      <SHIPMENT_COST>14</SHIPMENT_COST>
      <DELIVERY_TIME>9</DELIVERY_TIME>
      <MANUFACTURER>Philips Car Lights</MANUFACTURER>
      <WARRANTY>-</WARRANTY>
      <IMAGE>http://www.migvanhome.co.il/images/prudact/Philips.H27W-1_Main.Image.jpg</IMAGE>
      <TAX>1</TAX>
    </PRODUCT>
    <PRODUCT>
      <PRODUCT_URL>http://www.migvanhome.co.il/product.php?pid=968</PRODUCT_URL>
      <PRODUCT_NAME>נורת ערפל קדמי לרכב philips דגם H27W/2 זוויתי</PRODUCT_NAME>
      <MODEL>H27W/2</MODEL>
      <DETAILS>&amp;#9679     H27W2  .&amp;#9679  27W  12V.&amp;#9679   477lm.&amp;#9679   300 .&amp;#9679    &amp;#9679  Philips  .  12059C1.&amp;#9679   .  </DETAILS>
      <CATALOG_NUMBER>968</CATALOG_NUMBER>
      <CURRENCY>ILS</CURRENCY>
      <PRICE>29</PRICE>
      <SHIPMENT_COST>14</SHIPMENT_COST>
      <DELIVERY_TIME>9</DELIVERY_TIME>
      <MANUFACTURER>Philips Car Lights</MANUFACTURER>
      <WARRANTY>-</WARRANTY>
      <IMAGE>http://www.migvanhome.co.il/images/prudact/Philips.H27W-2_Main.Image.jpg</IMAGE>
      <TAX>1</TAX>
    </PRODUCT>
    <PRODUCT>
      <PRODUCT_URL>http://www.migvanhome.co.il/product.php?pid=969</PRODUCT_URL>
      <PRODUCT_NAME>נורה מיניאטורית לרכב 10 יח' Tungsram דגם W3W</PRODUCT_NAME>
      <MODEL>W3W</MODEL>
      <DETAILS>&amp;#9679    W3W.&amp;#9679  3W  12V.&amp;#9679   ...&amp;#9679 10  .&amp;#9679  Tungsram  H3&amp;#9679   .</DETAILS>
      <CATALOG_NUMBER>969</CATALOG_NUMBER>
      <CURRENCY>ILS</CURRENCY>
      <PRICE>10</PRICE>
      <SHIPMENT_COST>14</SHIPMENT_COST>
      <DELIVERY_TIME>9</DELIVERY_TIME>
      <MANUFACTURER>Tungsram</MANUFACTURER>
      <WARRANTY>-</WARRANTY>
      <IMAGE>http://www.migvanhome.co.il/images/prudact/Tungsram.W3W_Main.Image.jpg</IMAGE>
      <TAX>1</TAX>
    </PRODUCT>
    <PRODUCT>
      <PRODUCT_URL>http://www.migvanhome.co.il/product.php?pid=1008</PRODUCT_URL>
      <PRODUCT_NAME>נורה לרכב General Electric דגם W21W</PRODUCT_NAME>
      <MODEL>W21W</MODEL>
      <DETAILS>&amp;#9679      .&amp;#9679  21W  12V&amp;#9679  W3x16d.&amp;#9679      ..&amp;#9679     7440.&amp;#9679   .</DETAILS>
      <CATALOG_NUMBER>1008</CATALOG_NUMBER>
      <CURRENCY>ILS</CURRENCY>
      <PRICE>12</PRICE>
      <SHIPMENT_COST>14</SHIPMENT_COST>
      <DELIVERY_TIME>9</DELIVERY_TIME>
      <MANUFACTURER>General Electric</MANUFACTURER>
      <WARRANTY>-</WARRANTY>
      <IMAGE>http://www.migvanhome.co.il/images/prudact/General.Electric.W21W.jpg</IMAGE>
      <TAX>1</TAX>
    </PRODUCT>
    <PRODUCT>
      <PRODUCT_URL>http://www.migvanhome.co.il/product.php?pid=1009</PRODUCT_URL>
      <PRODUCT_NAME>נורה לרכב General Electric דגם W21/5W</PRODUCT_NAME>
      <MODEL>W21/5W</MODEL>
      <DETAILS>&amp;#9679      .&amp;#9679  215W  12V&amp;#9679  W3x16q.&amp;#9679      ..&amp;#9679     7443.&amp;#9679   .</DETAILS>
      <CATALOG_NUMBER>1009</CATALOG_NUMBER>
      <CURRENCY>ILS</CURRENCY>
      <PRICE>14</PRICE>
      <SHIPMENT_COST>14</SHIPMENT_COST>
      <DELIVERY_TIME>9</DELIVERY_TIME>
      <MANUFACTURER>General Electric</MANUFACTURER>
      <WARRANTY>-</WARRANTY>
      <IMAGE>http://www.migvanhome.co.il/images/prudact/General.Electric.W21.5W.jpg</IMAGE>
      <TAX>1</TAX>
    </PRODUCT>
    <PRODUCT>
      <PRODUCT_URL>http://www.migvanhome.co.il/product.php?pid=1010</PRODUCT_URL>
      <PRODUCT_NAME>זוג נורות לרכב General Electric דגם T4W</PRODUCT_NAME>
      <MODEL>T4W</MODEL>
      <DETAILS>&amp;#9679    .&amp;#9679  4W  12V.&amp;#9679  BA9s.&amp;#9679      ...&amp;#9679      2662.&amp;#9679   .  </DETAILS>
      <CATALOG_NUMBER>1010</CATALOG_NUMBER>
      <CURRENCY>ILS</CURRENCY>
      <PRICE>10</PRICE>
      <SHIPMENT_COST>14</SHIPMENT_COST>
      <DELIVERY_TIME>9</DELIVERY_TIME>
      <MANUFACTURER>General Electric</MANUFACTURER>
      <WARRANTY>-</WARRANTY>
      <IMAGE>http://www.migvanhome.co.il/images/prudact/General.Electric.T4W.jpg</IMAGE>
      <TAX>1</TAX>
    </PRODUCT>
    <PRODUCT>
      <PRODUCT_URL>http://www.migvanhome.co.il/product.php?pid=1011</PRODUCT_URL>
      <PRODUCT_NAME>נורה ראשית לרכב  General Electric דגם H1</PRODUCT_NAME>
      <MODEL>H1</MODEL>
      <DETAILS>&amp;#9679    .&amp;#9679  55W  12V.&amp;#9679  P14.5s.&amp;#9679     .&amp;#9679      H1.&amp;#9679   .  </DETAILS>
      <CATALOG_NUMBER>1011</CATALOG_NUMBER>
      <CURRENCY>ILS</CURRENCY>
      <PRICE>15</PRICE>
      <SHIPMENT_COST>14</SHIPMENT_COST>
      <DELIVERY_TIME>9</DELIVERY_TIME>
      <MANUFACTURER>General Electric</MANUFACTURER>
      <WARRANTY>-</WARRANTY>
      <IMAGE>http://www.migvanhome.co.il/images/prudact/General.Electric.H1.jpg</IMAGE>
      <TAX>1</TAX>
    </PRODUCT>
    <PRODUCT>
      <PRODUCT_URL>http://www.migvanhome.co.il/product.php?pid=1050</PRODUCT_URL>
      <PRODUCT_NAME>זוג נורות ראשיות לרכב Philips H1 דגם X-tremeVision</PRODUCT_NAME>
      <MODEL>H1</MODEL>
      <DETAILS>&amp;#9679    H1.&amp;#9679  55W   12V.&amp;#9679 130%   .&amp;#9679   3700K.&amp;#9679   1500lm.&amp;#9679   400 .&amp;#9679         .&amp;#9679     UV.&amp;#9679    Philips    .&amp;#9679    .&amp;#9679  Philips  XtremeVision.&amp;#9679   .  </DETAILS>
      <CATALOG_NUMBER>1050</CATALOG_NUMBER>
      <CURRENCY>ILS</CURRENCY>
      <PRICE>140</PRICE>
      <SHIPMENT_COST>14</SHIPMENT_COST>
      <DELIVERY_TIME>9</DELIVERY_TIME>
      <MANUFACTURER>Philips Car Lights</MANUFACTURER>
      <WARRANTY>-</WARRANTY>
      <IMAGE>http://www.migvanhome.co.il/images/prudact/Philips.headlighting.lamp.H1.X-tremeVision_Main.Image.jpg</IMAGE>
      <TAX>1</TAX>
    </PRODUCT>
    <PRODUCT>
      <PRODUCT_URL>http://www.migvanhome.co.il/product.php?pid=1051</PRODUCT_URL>
      <PRODUCT_NAME>זוג נורות ראשיות לרכב Philips H4 דגם X-tremeVision</PRODUCT_NAME>
      <MODEL>H4</MODEL>
      <DETAILS>&amp;#9679    H4.&amp;#9679  5560W   12V.&amp;#9679 130%   .&amp;#9679   3700K.&amp;#9679   1650lm.&amp;#9679   450 .&amp;#9679         .&amp;#9679     UV.&amp;#9679    Philips    .&amp;#9679   .&amp;#9679  Philips  XtremeVision.&amp;#9679   .  </DETAILS>
      <CATALOG_NUMBER>1051</CATALOG_NUMBER>
      <CURRENCY>ILS</CURRENCY>
      <PRICE>140</PRICE>
      <SHIPMENT_COST>14</SHIPMENT_COST>
      <DELIVERY_TIME>9</DELIVERY_TIME>
      <MANUFACTURER>Philips Car Lights</MANUFACTURER>
      <WARRANTY>-</WARRANTY>
      <IMAGE>http://www.migvanhome.co.il/images/prudact/Philips.headlighting.lamp.H4.X-tremeVision_Main.Image.jpg</IMAGE>
      <TAX>1</TAX>
    </PRODUCT>
    <PRODUCT>
      <PRODUCT_URL>http://www.migvanhome.co.il/product.php?pid=1052</PRODUCT_URL>
      <PRODUCT_NAME>נורה ראשית לרכב Philips HB3 דגם White Vision</PRODUCT_NAME>
      <MODEL>HB3</MODEL>
      <DETAILS>&amp;#9679     HB3.&amp;#9679  65W   12V.&amp;#9679  .&amp;#9679 60%   .&amp;#9679   4300K.&amp;#9679   1860lm.&amp;#9679   400 .&amp;#9679         .&amp;#9679     UV.&amp;#9679    Philips    .&amp;#9679   .&amp;#9679  Philips  WhiteVision.&amp;#9679   .  </DETAILS>
      <CATALOG_NUMBER>1052</CATALOG_NUMBER>
      <CURRENCY>ILS</CURRENCY>
      <PRICE>105</PRICE>
      <SHIPMENT_COST>14</SHIPMENT_COST>
      <DELIVERY_TIME>9</DELIVERY_TIME>
      <MANUFACTURER>Philips Car Lights</MANUFACTURER>
      <WARRANTY>-</WARRANTY>
      <IMAGE>http://www.migvanhome.co.il/images/prudact/Philips.headlighting.lamp.HB3.WhiteVision_Main.Image.jpg</IMAGE>
      <TAX>1</TAX>
    </PRODUCT>
    <PRODUCT>
      <PRODUCT_URL>http://www.migvanhome.co.il/product.php?pid=1053</PRODUCT_URL>
      <PRODUCT_NAME>נורה ראשית לרכב Tungsram דגם H1</PRODUCT_NAME>
      <MODEL>H1</MODEL>
      <DETAILS>&amp;#9679    H1.&amp;#9679  55W   12V.&amp;#9679     UV.&amp;#9679  Tungsram  H1.&amp;#9679   .</DETAILS>
      <CATALOG_NUMBER>1053</CATALOG_NUMBER>
      <CURRENCY>ILS</CURRENCY>
      <PRICE>16</PRICE>
      <SHIPMENT_COST>14</SHIPMENT_COST>
      <DELIVERY_TIME>9</DELIVERY_TIME>
      <MANUFACTURER>Tungsram</MANUFACTURER>
      <WARRANTY>-</WARRANTY>
      <IMAGE>http://www.migvanhome.co.il/images/prudact/Tungsram.Headlighting.lamp.H1.12V.55W.jpg</IMAGE>
      <TAX>1</TAX>
    </PRODUCT>
    <PRODUCT>
      <PRODUCT_URL>http://www.migvanhome.co.il/product.php?pid=1054</PRODUCT_URL>
      <PRODUCT_NAME>נורה ראשית לרכב Tungsram דגם H4</PRODUCT_NAME>
      <MODEL>H4</MODEL>
      <DETAILS>&amp;#9679    H4.&amp;#9679  5560W   12V.&amp;#9679     UV.&amp;#9679  Tungsram  H4.&amp;#9679   .</DETAILS>
      <CATALOG_NUMBER>1054</CATALOG_NUMBER>
      <CURRENCY>ILS</CURRENCY>
      <PRICE>20</PRICE>
      <SHIPMENT_COST>14</SHIPMENT_COST>
      <DELIVERY_TIME>9</DELIVERY_TIME>
      <MANUFACTURER>Tungsram</MANUFACTURER>
      <WARRANTY>-</WARRANTY>
      <IMAGE>http://www.migvanhome.co.il/images/prudact/Tungsram.Headlighting.lamp.H4.12V.55W.jpg</IMAGE>
      <TAX>1</TAX>
    </PRODUCT>
    <PRODUCT>
      <PRODUCT_URL>http://www.migvanhome.co.il/product.php?pid=1055</PRODUCT_URL>
      <PRODUCT_NAME>נורה ראשית לרכב Tungsram דגם H7</PRODUCT_NAME>
      <MODEL>H7</MODEL>
      <DETAILS>&amp;#9679    H7.&amp;#9679  55W   12V.&amp;#9679     UV.&amp;#9679  Tungsram  H7.&amp;#9679   .</DETAILS>
      <CATALOG_NUMBER>1055</CATALOG_NUMBER>
      <CURRENCY>ILS</CURRENCY>
      <PRICE>20</PRICE>
      <SHIPMENT_COST>14</SHIPMENT_COST>
      <DELIVERY_TIME>9</DELIVERY_TIME>
      <MANUFACTURER>Tungsram</MANUFACTURER>
      <WARRANTY>-</WARRANTY>
      <IMAGE>http://www.migvanhome.co.il/images/prudact/Tungsram.Headlighting.lamp.H7.12V.55W.jpg</IMAGE>
      <TAX>1</TAX>
    </PRODUCT>
    <PRODUCT>
      <PRODUCT_URL>http://www.migvanhome.co.il/product.php?pid=1089</PRODUCT_URL>
      <PRODUCT_NAME>זוג נורות איתות Nova דגם PY21W</PRODUCT_NAME>
      <MODEL>PY21W</MODEL>
      <DETAILS>&amp;#9679     .&amp;#9679  21W  12V.&amp;#9679    .&amp;#9679  Nova  PY21W.</DETAILS>
      <CATALOG_NUMBER>1089</CATALOG_NUMBER>
      <CURRENCY>ILS</CURRENCY>
      <PRICE>9</PRICE>
      <SHIPMENT_COST>14</SHIPMENT_COST>
      <DELIVERY_TIME>9</DELIVERY_TIME>
      <MANUFACTURER>Nova</MANUFACTURER>
      <WARRANTY>-</WARRANTY>
      <IMAGE>http://www.migvanhome.co.il/images/prudact/Noval.indicator.bulbs.PY21W_Main.Image.jpg</IMAGE>
      <TAX>1</TAX>
    </PRODUCT>
    <PRODUCT>
      <PRODUCT_URL>http://www.migvanhome.co.il/product.php?pid=1090</PRODUCT_URL>
      <PRODUCT_NAME>זוג נורות בלם Nova דגם R5W</PRODUCT_NAME>
      <MODEL>R5W</MODEL>
      <DETAILS>&amp;#9679    .&amp;#9679  5W  12V..&amp;#9679      .&amp;#9679  Nova  R5W.</DETAILS>
      <CATALOG_NUMBER>1090</CATALOG_NUMBER>
      <CURRENCY>ILS</CURRENCY>
      <PRICE>6</PRICE>
      <SHIPMENT_COST>14</SHIPMENT_COST>
      <DELIVERY_TIME>9</DELIVERY_TIME>
      <MANUFACTURER>Nova</MANUFACTURER>
      <WARRANTY>-</WARRANTY>
      <IMAGE>http://www.migvanhome.co.il/images/prudact/Noval.Stop.light.bulbs.R5W_Main.Image.jpg</IMAGE>
      <TAX>1</TAX>
    </PRODUCT>
    <PRODUCT>
      <PRODUCT_URL>http://www.migvanhome.co.il/product.php?pid=1154</PRODUCT_URL>
      <PRODUCT_NAME>זוג נורות Philips דגם W16W</PRODUCT_NAME>
      <MODEL>W16W</MODEL>
      <DETAILS>&amp;#9679    W16W.&amp;#9679  16W  12V.&amp;#9679   310lm.&amp;#9679   700 .&amp;#9679      .&amp;#9679 2  .&amp;#9679  Philips  .  1206B2.&amp;#9679   .  </DETAILS>
      <CATALOG_NUMBER>1154</CATALOG_NUMBER>
      <CURRENCY>ILS</CURRENCY>
      <PRICE>18</PRICE>
      <SHIPMENT_COST>14</SHIPMENT_COST>
      <DELIVERY_TIME/>
      <MANUFACTURER>Philips Car Lights</MANUFACTURER>
      <WARRANTY>Best-Store</WARRANTY>
      <IMAGE>http://www.migvanhome.co.il/images/prudact/Philips.Pair.bulbs.W16W_Main.Image.jpg</IMAGE>
      <TAX>1</TAX>
    </PRODUCT>
    <PRODUCT>
      <PRODUCT_URL>http://www.migvanhome.co.il/product.php?pid=1163</PRODUCT_URL>
      <PRODUCT_NAME>נורה ראשית לרכב H4 תוצרת Philips דגם LongLife</PRODUCT_NAME>
      <MODEL>H4</MODEL>
      <DETAILS>&amp;#9679     H412972LLECOB1.&amp;#9679  5560W  12V  P43t38.&amp;#9679         .&amp;#9679     UV.&amp;#9679   3100K.&amp;#9679   10001650lm.&amp;#9679   3000 .&amp;#9679      .&amp;#9679  Philips  LongLife EcoVision.&amp;#9679   .  </DETAILS>
      <CATALOG_NUMBER>1163</CATALOG_NUMBER>
      <CURRENCY>ILS</CURRENCY>
      <PRICE>39</PRICE>
      <SHIPMENT_COST>14</SHIPMENT_COST>
      <DELIVERY_TIME>9</DELIVERY_TIME>
      <MANUFACTURER>Car.Lights.Philips</MANUFACTURER>
      <WARRANTY>-</WARRANTY>
      <IMAGE>http://www.migvanhome.co.il/images/prudact/Philips.headlighting.lamp.H4.Long.Life.Ecovision.jpg</IMAGE>
      <TAX>1</TAX>
    </PRODUCT>
    <PRODUCT>
      <PRODUCT_URL>http://www.migvanhome.co.il/product.php?pid=1164</PRODUCT_URL>
      <PRODUCT_NAME>נורה ראשית לרכב H7 תוצרת Philips דגם LongLife</PRODUCT_NAME>
      <MODEL>H7</MODEL>
      <DETAILS>&amp;#9679     H712972LLECOB1.&amp;#9679  55W  12V  PX26d.&amp;#9679         .&amp;#9679     UV.&amp;#9679   3100K.&amp;#9679   1500lm.&amp;#9679   1500 .&amp;#9679      .&amp;#9679  Philips  LongLife EcoVision.&amp;#9679   .  </DETAILS>
      <CATALOG_NUMBER>1164</CATALOG_NUMBER>
      <CURRENCY>ILS</CURRENCY>
      <PRICE>49</PRICE>
      <SHIPMENT_COST>14</SHIPMENT_COST>
      <DELIVERY_TIME>9</DELIVERY_TIME>
      <MANUFACTURER>Philips Car Lights</MANUFACTURER>
      <WARRANTY>-</WARRANTY>
      <IMAGE>http://www.migvanhome.co.il/images/prudact/Philips.headlighting.lamp.H7.Long.Life.Ecovision.jpg</IMAGE>
      <TAX>1</TAX>
    </PRODUCT>
    <PRODUCT>
      <PRODUCT_URL>http://www.migvanhome.co.il/product.php?pid=1382</PRODUCT_URL>
      <PRODUCT_NAME>זוג נורות בלם Nova דגם P21/5W</PRODUCT_NAME>
      <MODEL>P21/5W</MODEL>
      <DETAILS>&amp;#9679       .&amp;#9679  215W  12V.&amp;#9679   .&amp;#9679  Nova  P215W.</DETAILS>
      <CATALOG_NUMBER>1382</CATALOG_NUMBER>
      <CURRENCY>ILS</CURRENCY>
      <PRICE>6</PRICE>
      <SHIPMENT_COST>14</SHIPMENT_COST>
      <DELIVERY_TIME>9</DELIVERY_TIME>
      <MANUFACTURER>Nova</MANUFACTURER>
      <WARRANTY>-</WARRANTY>
      <IMAGE>http://www.migvanhome.co.il/images/prudact/Nova.Stop.light.bulbs.P21.5W.jpg</IMAGE>
      <TAX>1</TAX>
    </PRODUCT>
    <PRODUCT>
      <PRODUCT_URL>http://www.migvanhome.co.il/product.php?pid=1383</PRODUCT_URL>
      <PRODUCT_NAME>זוג נורות בלם Nova דגם W21/5W</PRODUCT_NAME>
      <MODEL>W21/5W</MODEL>
      <DETAILS>&amp;#9679       .&amp;#9679  215W  12V.&amp;#9679       ...&amp;#9679  Nova  W215W.</DETAILS>
      <CATALOG_NUMBER>1383</CATALOG_NUMBER>
      <CURRENCY>ILS</CURRENCY>
      <PRICE>14</PRICE>
      <SHIPMENT_COST>14</SHIPMENT_COST>
      <DELIVERY_TIME>9</DELIVERY_TIME>
      <MANUFACTURER>Nova</MANUFACTURER>
      <WARRANTY>-</WARRANTY>
      <IMAGE>http://www.migvanhome.co.il/images/prudact/Nova.Stop.light.bulbs.W21.5W.jpg</IMAGE>
      <TAX>1</TAX>
    </PRODUCT>
    <PRODUCT>
      <PRODUCT_URL>http://www.migvanhome.co.il/product.php?pid=1384</PRODUCT_URL>
      <PRODUCT_NAME>זוג נורות חניה Nova דגם 5W</PRODUCT_NAME>
      <MODEL>5W</MODEL>
      <DETAILS>&amp;#9679     .&amp;#9679  5W  12V.&amp;#9679   .&amp;#9679  Nova  5W.</DETAILS>
      <CATALOG_NUMBER>1384</CATALOG_NUMBER>
      <CURRENCY>ILS</CURRENCY>
      <PRICE>5</PRICE>
      <SHIPMENT_COST>14</SHIPMENT_COST>
      <DELIVERY_TIME>9</DELIVERY_TIME>
      <MANUFACTURER>Nova</MANUFACTURER>
      <WARRANTY>-</WARRANTY>
      <IMAGE>http://www.migvanhome.co.il/images/prudact/Nova.Parking.light.bulbs.5W.jpg</IMAGE>
      <TAX>1</TAX>
    </PRODUCT>
    <PRODUCT>
      <PRODUCT_URL>http://www.migvanhome.co.il/product.php?pid=1385</PRODUCT_URL>
      <PRODUCT_NAME>זוג נורות בלם Nova דגם P21W</PRODUCT_NAME>
      <MODEL>21W</MODEL>
      <DETAILS>&amp;#9679       .&amp;#9679  21W  12V.&amp;#9679      ...&amp;#9679  Nova  P21W.</DETAILS>
      <CATALOG_NUMBER>1385</CATALOG_NUMBER>
      <CURRENCY>ILS</CURRENCY>
      <PRICE>6</PRICE>
      <SHIPMENT_COST>14</SHIPMENT_COST>
      <DELIVERY_TIME>9</DELIVERY_TIME>
      <MANUFACTURER>Nova</MANUFACTURER>
      <WARRANTY>-</WARRANTY>
      <IMAGE>http://www.migvanhome.co.il/images/prudact/Nova.Stop.light.bulbs.P21W.jpg</IMAGE>
      <TAX>1</TAX>
    </PRODUCT>
    <PRODUCT>
      <PRODUCT_URL>http://www.migvanhome.co.il/product.php?pid=1455</PRODUCT_URL>
      <PRODUCT_NAME>נורה ראשית לרכב Philips HB4 דגם White Vision</PRODUCT_NAME>
      <MODEL>HB4</MODEL>
      <DETAILS>&amp;#9679     HB49006.&amp;#9679  55W   12V.&amp;#9679  .&amp;#9679 60%   .&amp;#9679   3700K.&amp;#9679   1095lm.&amp;#9679   400 .&amp;#9679         .&amp;#9679     UV.&amp;#9679    Philips    .&amp;#9679   .&amp;#9679  Philips  WhiteVision.&amp;#9679   .  </DETAILS>
      <CATALOG_NUMBER>1455</CATALOG_NUMBER>
      <CURRENCY>ILS</CURRENCY>
      <PRICE>105</PRICE>
      <SHIPMENT_COST>14</SHIPMENT_COST>
      <DELIVERY_TIME>9</DELIVERY_TIME>
      <MANUFACTURER>Philips Car Lights</MANUFACTURER>
      <WARRANTY>-</WARRANTY>
      <IMAGE>http://www.migvanhome.co.il/images/prudact/Philips.headlighting.lamp.HB4.WhiteVision.jpg</IMAGE>
      <TAX>1</TAX>
    </PRODUCT>
    <PRODUCT>
      <PRODUCT_URL>http://www.migvanhome.co.il/product.php?pid=1456</PRODUCT_URL>
      <PRODUCT_NAME>נורה ראשית לרכב Tungsram דגם H11</PRODUCT_NAME>
      <MODEL>H11</MODEL>
      <DETAILS>&amp;#9679    H11.&amp;#9679  55W   12V.&amp;#9679     UV.&amp;#9679  Tungsram  H11.&amp;#9679   .</DETAILS>
      <CATALOG_NUMBER>1456</CATALOG_NUMBER>
      <CURRENCY>ILS</CURRENCY>
      <PRICE>39</PRICE>
      <SHIPMENT_COST>14</SHIPMENT_COST>
      <DELIVERY_TIME>9</DELIVERY_TIME>
      <MANUFACTURER>Tungsram</MANUFACTURER>
      <WARRANTY>-</WARRANTY>
      <IMAGE>http://www.migvanhome.co.il/images/prudact/Tungsram.Head.lighting.lamp.H11.jpg</IMAGE>
      <TAX>1</TAX>
    </PRODUCT>
    <PRODUCT>
      <PRODUCT_URL>http://www.migvanhome.co.il/product.php?pid=1849</PRODUCT_URL>
      <PRODUCT_NAME>נורה ראשית לרכב Tungsram דגם HB3</PRODUCT_NAME>
      <MODEL>HB3</MODEL>
      <DETAILS>&amp;#9679    HB39005.&amp;#9679  60W   12V.&amp;#9679   P20d.&amp;#9679     UV.&amp;#9679  Tungsram  GE   HB3.&amp;#9679   .</DETAILS>
      <CATALOG_NUMBER>1849</CATALOG_NUMBER>
      <CURRENCY>ILS</CURRENCY>
      <PRICE>22</PRICE>
      <SHIPMENT_COST>14</SHIPMENT_COST>
      <DELIVERY_TIME>9</DELIVERY_TIME>
      <MANUFACTURER>Tungsram</MANUFACTURER>
      <WARRANTY>-</WARRANTY>
      <IMAGE>http://www.migvanhome.co.il/images/prudact/Tungsram.headlighting.lamp.HB3.jpg</IMAGE>
      <TAX>1</TAX>
    </PRODUCT>
    <PRODUCT>
      <PRODUCT_URL>http://www.migvanhome.co.il/product.php?pid=1850</PRODUCT_URL>
      <PRODUCT_NAME>נורה ראשית לרכב Tungsram דגם HB4</PRODUCT_NAME>
      <MODEL>HB4</MODEL>
      <DETAILS>&amp;#9679    HB49006.&amp;#9679  51W   12V.&amp;#9679   P22d.&amp;#9679     UV.&amp;#9679  Tungsram  GE   HB4.&amp;#9679   .</DETAILS>
      <CATALOG_NUMBER>1850</CATALOG_NUMBER>
      <CURRENCY>ILS</CURRENCY>
      <PRICE>22</PRICE>
      <SHIPMENT_COST>14</SHIPMENT_COST>
      <DELIVERY_TIME>9</DELIVERY_TIME>
      <MANUFACTURER>Tungsram</MANUFACTURER>
      <WARRANTY>-</WARRANTY>
      <IMAGE>http://www.migvanhome.co.il/images/prudact/Tungsram.headlighting.lamp.HB4.jpg</IMAGE>
      <TAX>1</TAX>
    </PRODUCT>
  </PRODUCTS>
</STORE>
